{
  "$schema": "https://json-schema.org/draft/2020-12/schema",
  "title": "Folktale Morphology Canvas Input",
  "type": "object",
  "required": ["item", "tale_type", "function_identification", "sequence_clarity", "role_mapping"],
  "properties": {
    "item": {"type": "string"},
    "tale_type": {"type": "string"},
    "function_identification": {"type": "number", "minimum": 0, "maximum": 1},
    "sequence_clarity": {"type": "number", "minimum": 0, "maximum": 1},
    "role_mapping": {"type": "number", "minimum": 0, "maximum": 1},
    "variation_tracking": {"type": "number", "minimum": 0, "maximum": 1},
    "context_notes": {"type": "number", "minimum": 0, "maximum": 1},
    "order_coherence": {"type": "number", "minimum": 0, "maximum": 1},
    "transition_logic": {"type": "number", "minimum": 0, "maximum": 1},
    "gap_management": {"type": "number", "minimum": 0, "maximum": 1},
    "repetition_awareness": {"type": "number", "minimum": 0, "maximum": 1},
    "closure_handling": {"type": "number", "minimum": 0, "maximum": 1},
    "performance_context": {"type": "number", "minimum": 0, "maximum": 1},
    "cultural_specificity": {"type": "number", "minimum": 0, "maximum": 1},
    "language_notes": {"type": "number", "minimum": 0, "maximum": 1},
    "tradition_review": {"type": "number", "minimum": 0, "maximum": 1},
    "ethical_governance": {"type": "number", "minimum": 0, "maximum": 1},
    "universalization_risk": {"type": "number", "minimum": 0, "maximum": 1},
    "cultural_erasure_risk": {"type": "number", "minimum": 0, "maximum": 1},
    "performance_omission": {"type": "number", "minimum": 0, "maximum": 1},
    "variation_omission": {"type": "number", "minimum": 0, "maximum": 1},
    "archive_bias": {"type": "number", "minimum": 0, "maximum": 1},
    "community_sensitivity": {"type": "number", "minimum": 0, "maximum": 1},
    "public_consequence": {"type": "number", "minimum": 0, "maximum": 1},
    "owner": {"type": "string"},
    "status": {"type": "string"}
  }
}
